reddit_image_downloader/__init__.py
reddit_image_downloader/cli.py
reddit_image_downloader/config.json
reddit_image_downloader/main.py
reddit_image_downloader/spinner.py
tests/__init__.py
tests/package_test.py
tests/test_main.py
reddit_image_downloader-0.2.0.dist-info/LICENSE
reddit_image_downloader-0.2.0.dist-info/METADATA
reddit_image_downloader-0.2.0.dist-info/WHEEL
reddit_image_downloader-0.2.0.dist-info/entry_points.txt
reddit_image_downloader-0.2.0.dist-info/top_level.txt
reddit_image_downloader-0.2.0.dist-info/RECORD
