Metadata-Version: 2.1
Name: reddit_image_downloader
Version: 0.2.0
Summary: A tool to download images from Reddit posts and comments and save them into a ZIP file.
Home-page: https://github.com/iamrishu11/Reddit-Image-Downloader
Author: Rishank Jain
Author-email: rishankj749@gmail.com
License: MIT
Classifier: Programming Language :: Python :: 3
Classifier: License :: OSI Approved :: MIT License
Classifier: Operating System :: OS Independent
Requires-Python: >=3.6
License-File: LICENSE
Requires-Dist: praw >=7.8.1
Requires-Dist: requests >=2.28.2
Requires-Dist: tqdm >=4.65.0
Requires-Dist: setuptools
